github3apps/__init__.py
github3apps/github3apps.py
divlibgithub3apps-1.0.8.dist-info/LICENSE
divlibgithub3apps-1.0.8.dist-info/METADATA
divlibgithub3apps-1.0.8.dist-info/WHEEL
divlibgithub3apps-1.0.8.dist-info/top_level.txt
divlibgithub3apps-1.0.8.dist-info/RECORD
