Metadata-Version: 2.1
Name: divlibgithub3apps
Version: 1.0.8
Summary: Access the Github API as an Application
Home-page: https://github.com/onediversified/div.lib.github3apps
Author: OneDiversified
Author-email: github@onediversified.com
License: UNKNOWN
Download-URL: https://github.com/onediversified/div.lib.github3apps/archive/v1.0.8.tar.gz
Keywords: automation github apps git
Platform: UNKNOWN
Classifier: Development Status :: 4 - Beta
Classifier: License :: OSI Approved :: MIT License
Classifier: Intended Audience :: Developers
Classifier: Topic :: Software Development :: Version Control
Classifier: Programming Language :: Python :: 3
Requires-Python: >=3.10
License-File: LICENSE
Requires-Dist: cryptography (>=39.0.2)
Requires-Dist: github3.py (>=3.2.0)
Requires-Dist: pyjwt (>=2.6.0)
Requires-Dist: requests (>=2.28.2)
Provides-Extra: dev
Requires-Dist: pypandoc ; extra == 'dev'
Requires-Dist: twine ; extra == 'dev'
Requires-Dist: wheel ; extra == 'dev'
